rogue_gym/__init__.py
rogue_gym/cli.py
rogue_gym/rainy_impls.py
rogue_gym/envs/__init__.py
rogue_gym/envs/parallel.py
rogue_gym/envs/rogue_env.py
rogue_gym/envs/wrappers.py
rogue_gym_python/_rogue_gym.cp37-win_amd64.pyd
rogue_gym-0.0.2.dist-info/METADATA
rogue_gym-0.0.2.dist-info/WHEEL
rogue_gym-0.0.2.dist-info/top_level.txt
rogue_gym-0.0.2.dist-info/RECORD
