Metadata-Version: 2.1
Name: rogue-gym
Version: 0.0.2
Summary: OpenAI gym environment for rogue-gym
Home-page: https://github.com/kngwyu/rogue-gym
Author: Yuji Kanagawa
Author-email: yuji.kngw.80s.revive@gmail.com
License: MIT
Project-URL: Code, https://github.com/kngwyu/rogue-gym
Project-URL: Issue tracker, https://github.com/kngwyu/rogue-gym/issues
Platform: UNKNOWN
Classifier: License :: OSI Approved :: MIT License
Classifier: License :: OSI Approved :: Apache Software License
Classifier: Development Status :: 3 - Alpha
Classifier: Intended Audience :: Developers
Classifier: Natural Language :: English
Classifier: Operating System :: POSIX :: Linux
Classifier: Programming Language :: Rust
Classifier: Programming Language :: Python :: 3.6
Classifier: Programming Language :: Python :: 3.7
Requires-Dist: numpy
Requires-Dist: gym
Provides-Extra: rainy
Requires-Dist: rainy ; extra == 'rainy'
